pyproject.toml
cpp_linter_hooks/__init__.py
cpp_linter_hooks/clang_format.py
cpp_linter_hooks/clang_tidy.py
cpp_linter_hooks/util.py
cpp_linter_hooks/versions.py
cpp_linter_hooks-1.1.11.dist-info/licenses/LICENSE
cpp_linter_hooks-1.1.11.dist-info/METADATA
cpp_linter_hooks-1.1.11.dist-info/WHEEL
cpp_linter_hooks-1.1.11.dist-info/entry_points.txt
cpp_linter_hooks-1.1.11.dist-info/top_level.txt
cpp_linter_hooks-1.1.11.dist-info/RECORD
