Metadata-Version: 2.4
Name: cpp_linter_hooks
Version: 1.1.11
Summary: Automatically formats and lints C/C++ code using clang-format and clang-tidy
Author-email: Xianpeng Shen <xianpeng.shen@gmail.com>
License-Expression: MIT
Project-URL: source, https://github.com/cpp-linter/cpp-linter-hooks
Project-URL: tracker, https://github.com/cpp-linter/cpp-linter-hooks/issues
Keywords: clang,clang-format,clang-tidy,pre-commit,pre-commit-hooks
Classifier: Development Status :: 5 - Production/Stable
Classifier: Intended Audience :: Developers
Classifier: Intended Audience :: System Administrators
Classifier: Intended Audience :: Information Technology
Classifier: Natural Language :: English
Classifier: Operating System :: Microsoft :: Windows
Classifier: Operating System :: POSIX :: Linux
Classifier: Operating System :: MacOS
Classifier: Programming Language :: Python :: 3.9
Classifier: Programming Language :: Python :: 3.10
Classifier: Programming Language :: Python :: 3.11
Classifier: Programming Language :: Python :: 3.12
Classifier: Programming Language :: Python :: 3.13
Classifier: Programming Language :: Python :: 3.14
Classifier: Topic :: Software Development :: Build Tools
Requires-Python: >=3.9
License-File: LICENSE
Requires-Dist: pip>=20.3
Requires-Dist: tomli>=1.1.0; python_version < "3.11"
Requires-Dist: setuptools>=45.0.0
Requires-Dist: clang-format==21.1.7
Requires-Dist: clang-tidy==21.1.6
Dynamic: license-file
